{
  "image": "label_Data_20250414_101301.png",
  "bboxes": [
    {
      "bbox": [
        273.7038879394531,
        115.73796081542969,
        1271.396240234375,
        715.4396362304688
      ],
      "text_score": 0.6048657894134521,
      "label": "rectangular kraft parcel"
    },
    {
      "bbox": [
        277.1902160644531,
        118.28419494628906,
        1184.05029296875,
        716.0032348632812
      ],
      "text_score": 0.2422056347131729,
      "label": "rectangular kraft parcel"
    }
  ]
}