{
  "image": "label_Data_20250506_144354.png",
  "bboxes": [
    {
      "bbox": [
        277.89990234375,
        238.05433654785156,
        343.0453796386719,
        299.2729797363281
      ],
      "text_score": 0.5945512652397156,
      "label": "white product labels"
    },
    {
      "bbox": [
        849.46875,
        128.7308349609375,
        904.3395385742188,
        149.1037139892578
      ],
      "text_score": 0.1710611879825592,
      "label": "white product labels"
    }
  ]
}