{
  "image": "label_Data_20250506_142540.png",
  "bboxes": [
    {
      "bbox": [
        257.6150207519531,
        147.6436004638672,
        444.4261169433594,
        394.53497314453125
      ],
      "text_score": 0.10818895697593689,
      "label": "tan paper - wrapped box"
    },
    {
      "bbox": [
        439.82940673828125,
        142.8669891357422,
        621.2706909179688,
        389.2972717285156
      ],
      "text_score": 0.09268777817487717,
      "label": "tan paper - wrapped box"
    }
  ]
}