{
  "image": "label_Data_20250506_142532.png",
  "bboxes": [
    {
      "bbox": [
        457.65313720703125,
        233.689697265625,
        520.6971435546875,
        294.2535095214844
      ],
      "text_score": 0.5592900514602661,
      "label": "white product labels"
    },
    {
      "bbox": [
        278.1796569824219,
        238.33651733398438,
        342.90863037109375,
        299.4606018066406
      ],
      "text_score": 0.5515737533569336,
      "label": "white product labels"
    }
  ]
}