{
  "image": "label_Data_20250506_135715.png",
  "bboxes": [
    {
      "bbox": [
        245.61874389648438,
        378.1676025390625,
        441.62835693359375,
        637.6732788085938
      ],
      "text_score": 0.4277552366256714,
      "label": "rectangular cardboard carton"
    },
    {
      "bbox": [
        439.9676208496094,
        372.5555725097656,
        628.9214477539062,
        631.0698852539062
      ],
      "text_score": 0.42536652088165283,
      "label": "rectangular cardboard carton"
    },
    {
      "bbox": [
        440.1278381347656,
        143.28524780273438,
        618.9817504882812,
        375.8564147949219
      ],
      "text_score": 0.40922078490257263,
      "label": "rectangular cardboard carton"
    },
    {
      "bbox": [
        612.0751342773438,
        139.78109741210938,
        795.0924072265625,
        372.255859375
      ],
      "text_score": 0.4101654887199402,
      "label": "rectangular cardboard carton"
    },
    {
      "bbox": [
        256.8658447265625,
        147.9166259765625,
        443.0335998535156,
        381.6188049316406
      ],
      "text_score": 0.41727152466773987,
      "label": "rectangular cardboard carton"
    },
    {
      "bbox": [
        619.5842895507812,
        367.2684326171875,
        816.29052734375,
        623.3919677734375
      ],
      "text_score": 0.4234579801559448,
      "label": "rectangular cardboard carton"
    },
    {
      "bbox": [
        780.0289306640625,
        132.72772216796875,
        973.0530395507812,
        375.341064453125
      ],
      "text_score": 0.4196479320526123,
      "label": "rectangular cardboard carton"
    }
  ]
}