{
  "image": "label_Data_20250506_135055.png",
  "bboxes": [
    {
      "bbox": [
        422.0212097167969,
        109.59564971923828,
        617.8792724609375,
        374.3277587890625
      ],
      "text_score": 0.328529417514801,
      "label": "brown cardboard shipping box"
    },
    {
      "bbox": [
        619.3060913085938,
        366.625732421875,
        815.6014404296875,
        623.1281127929688
      ],
      "text_score": 0.30985841155052185,
      "label": "brown cardboard shipping box"
    },
    {
      "bbox": [
        610.6173095703125,
        101.32915496826172,
        811.1499633789062,
        369.78863525390625
      ],
      "text_score": 0.3372035324573517,
      "label": "brown cardboard shipping box"
    },
    {
      "bbox": [
        439.6541748046875,
        373.4085693359375,
        629.0536499023438,
        631.224365234375
      ],
      "text_score": 0.319121390581131,
      "label": "brown cardboard shipping box"
    },
    {
      "bbox": [
        217.44325256347656,
        109.58544921875,
        425.93817138671875,
        377.7714538574219
      ],
      "text_score": 0.3242354094982147,
      "label": "brown cardboard shipping box"
    },
    {
      "bbox": [
        245.99290466308594,
        377.9775085449219,
        441.45361328125,
        637.7339477539062
      ],
      "text_score": 0.3268083333969116,
      "label": "brown cardboard shipping box"
    },
    {
      "bbox": [
        795.9515380859375,
        132.6112518310547,
        973.7359619140625,
        365.4595642089844
      ],
      "text_score": 0.3007456064224243,
      "label": "brown cardboard shipping box"
    },
    {
      "bbox": [
        796.2369384765625,
        359.7401123046875,
        1002.6053466796875,
        616.7927856445312
      ],
      "text_score": 0.3259495198726654,
      "label": "brown cardboard shipping box"
    },
    {
      "bbox": [
        246.871337890625,
        378.8387145996094,
        440.26190185546875,
        636.3014526367188
      ],
      "text_score": 0.08151976019144058,
      "label": "brown cardboard shipping box"
    }
  ]
}