{
  "image": "label_Data_20250506_155229.png",
  "bboxes": [
    {
      "bbox": [
        789.8494873046875,
        303.1986083984375,
        1173.999755859375,
        713.7758178710938
      ],
      "text_score": 0.18713268637657166,
      "label": "brown cardboard shipping box"
    },
    {
      "bbox": [
        552.918212890625,
        343.8002014160156,
        856.2612915039062,
        715.7149658203125
      ],
      "text_score": 0.19682618975639343,
      "label": "brown cardboard shipping box"
    },
    {
      "bbox": [
        550.1575317382812,
        120.3520736694336,
        791.0189208984375,
        377.8585205078125
      ],
      "text_score": 0.18594719469547272,
      "label": "brown cardboard shipping box"
    },
    {
      "bbox": [
        327.28692626953125,
        155.68658447265625,
        555.8660888671875,
        411.2835388183594
      ],
      "text_score": 0.17441026866436005,
      "label": "brown cardboard shipping box"
    },
    {
      "bbox": [
        280.984619140625,
        379.2707824707031,
        557.1361083984375,
        716.4545288085938
      ],
      "text_score": 0.1677633374929428,
      "label": "brown cardboard shipping box"
    },
    {
      "bbox": [
        747.0867919921875,
        83.48690032958984,
        1044.4542236328125,
        339.96527099609375
      ],
      "text_score": 0.17328819632530212,
      "label": "brown cardboard shipping box"
    },
    {
      "bbox": [
        37.189674377441406,
        410.6183776855469,
        327.8795166015625,
        716.947509765625
      ],
      "text_score": 0.15713684260845184,
      "label": "brown cardboard shipping box"
    },
    {
      "bbox": [
        113.28082275390625,
        185.60784912109375,
        363.7960205078125,
        442.8504638671875
      ],
      "text_score": 0.17441026866436005,
      "label": "brown cardboard shipping box"
    }
  ]
}