{
  "image": "label_Data_20250414_131017.png",
  "bboxes": [
    {
      "bbox": [
        596.0849609375,
        169.88815307617188,
        824.5568237304688,
        398.0765075683594
      ],
      "text_score": 0.7592254281044006,
      "label": "white product labels"
    },
    {
      "bbox": [
        595.6300048828125,
        170.10472106933594,
        824.597900390625,
        398.1009826660156
      ],
      "text_score": 0.2689414322376251,
      "label": "white product labels"
    }
  ]
}