{
  "image": "label_Data_20250414_131017.png",
  "bboxes": [
    {
      "bbox": [
        595.9482421875,
        170.01292419433594,
        824.531494140625,
        398.09490966796875
      ],
      "text_score": 0.7310585379600525,
      "label": "white product labels"
    },
    {
      "bbox": [
        595.8802490234375,
        170.1432647705078,
        824.4143676757812,
        398.0469055175781
      ],
      "text_score": 0.2829881012439728,
      "label": "white product labels"
    }
  ]
}